storyscript/SymbolTable.py
storyscript/__main__.py
storyscript/benchmarking.py
storyscript/cachelogger.py
storyscript/executor.py
storyscript/langData.py
storyscript/langParser.py
storyscript/lexer.py
storyscript/processor.py
storyscript/tests.py
storyscript_mathparse/mathInterpreter.py
storyscript_mathparse/mathLexer.py
storyscript_mathparse/mathParser.py
storyscript_mathparse/mathProcessor.py
storyscript_mathparse/nodes.py
storyscript_mathparse/tokens.py
storyscript_mathparse/values.py
storyscript-0.0.3.dist-info/LICENSE
storyscript-0.0.3.dist-info/METADATA
storyscript-0.0.3.dist-info/WHEEL
storyscript-0.0.3.dist-info/entry_points.txt
storyscript-0.0.3.dist-info/top_level.txt
storyscript-0.0.3.dist-info/RECORD
