Metadata-Version: 2.1
Name: storyscript
Version: 0.0.3
Summary: An interpreted programming language.
Home-page: https://github.com/storyscriptorg/StoryScript
Author: lines-of-code
Author-email: admin@susite.ga
License: MIT
Platform: UNKNOWN
Classifier: Development Status :: 3 - Alpha
Classifier: Programming Language :: Python :: 3
Requires-Dist: Pyinstrument
Requires-Dist: colorama (==0.4.4)
Requires-Dist: numpy (==1.21.1)
